aitoolz/__init__.py
aitoolz/find_imports.py
aitoolz/make_project.py
aitoolz/py.typed
aitoolz/utils.py
aitoolz/resources/pkg_templates/.gitignore
aitoolz/resources/pkg_templates/README.md
aitoolz/resources/pkg_templates/__init__.py
aitoolz/resources/pkg_templates/hello_world.py
aitoolz/resources/pkg_templates/noxfile.py
aitoolz/resources/pkg_templates/py.typed
aitoolz/resources/pkg_templates/pyproject.toml
aitoolz/resources/pkg_templates/python-package-cd.yml
aitoolz/resources/pkg_templates/python-package-ci.yml
aitoolz/resources/pkg_templates/test_hello_world.py
aitoolz-0.2.0.dist-info/LICENSE
aitoolz-0.2.0.dist-info/METADATA
aitoolz-0.2.0.dist-info/WHEEL
aitoolz-0.2.0.dist-info/entry_points.txt
aitoolz-0.2.0.dist-info/top_level.txt
aitoolz-0.2.0.dist-info/RECORD
