Metadata-Version: 2.1
Name: aitoolz
Version: 0.2.0
Summary: Python toolz, by Alex Ioannides (AI).
Author-email: Alex Ioannides <alex@bodyworkml.com>
Maintainer-email: Alex Ioannides <alex@bodyworkml.com>
License: Apache License
Project-URL: Homepage, https://github.com/AlexIoannides/aitoolz
Project-URL: Bug Tracker, https://github.com/AlexIoannides/aitoolz/issues
Requires-Python: >=3.8
License-File: LICENSE
Provides-Extra: deploy
Requires-Dist: build >=1.0.0 ; extra == 'deploy'
Requires-Dist: pip >=23.2.0 ; extra == 'deploy'
Requires-Dist: setuptools >=68.0.0 ; extra == 'deploy'
Requires-Dist: twine >=4.0.0 ; extra == 'deploy'
Requires-Dist: wheel >=0.41.0 ; extra == 'deploy'
Provides-Extra: dev
Requires-Dist: black ==23.9.1 ; extra == 'dev'
Requires-Dist: python-dotenv >=1.0.0 ; extra == 'dev'
Requires-Dist: icecream >=2.0.0 ; extra == 'dev'
Requires-Dist: ipython >=8.16.0 ; extra == 'dev'
Requires-Dist: mypy ==1.5.1 ; extra == 'dev'
Requires-Dist: nox ==2023.4.22 ; extra == 'dev'
Requires-Dist: pytest ==7.4.2 ; extra == 'dev'
Requires-Dist: ruff ==0.0.290 ; extra == 'dev'
